dns_local/__init__.py
dns_local/__main__.py
dns_local/_version.py
dns_local/dnsserver.py
dns_local/exceptions.py
dns_local-2.1.2.dist-info/LICENSE
dns_local-2.1.2.dist-info/METADATA
dns_local-2.1.2.dist-info/WHEEL
dns_local-2.1.2.dist-info/entry_points.txt
dns_local-2.1.2.dist-info/top_level.txt
dns_local-2.1.2.dist-info/RECORD
