Metadata-Version: 2.1
Name: dns_local
Version: 2.1.2
Summary: Simple python3 DNS server
Author-email: doronz88 <doron88@gmail.com>
Maintainer-email: doronz88 <doron88@gmail.com>
License: GNU GENERAL PUBLIC LICENSE Version 3, 29 June 2007
Project-URL: Homepage, https://github.com/doronz88/dns_local
Project-URL: Bug Reports, https://github.com/doronz88/dns_local/issues
Keywords: dns,protocol
Classifier: Development Status :: 5 - Production/Stable
Classifier: License :: OSI Approved :: GNU General Public License v3 or later (GPLv3+)
Classifier: Programming Language :: Python :: 3
Classifier: Programming Language :: Python :: 3.8
Classifier: Programming Language :: Python :: 3.9
Classifier: Programming Language :: Python :: 3.10
Classifier: Programming Language :: Python :: 3.11
Classifier: Programming Language :: Python :: 3.12
Classifier: Programming Language :: Python :: 3 :: Only
Requires-Python: >=3.8
License-File: LICENSE
Requires-Dist: ifaddr
Requires-Dist: click
Requires-Dist: coloredlogs
Requires-Dist: dnslib
Provides-Extra: test
Requires-Dist: pytest ; extra == 'test'
